test_poetry_nr/__init__.py
test_poetry_nr-0.1.1.dist-info/METADATA
test_poetry_nr-0.1.1.dist-info/WHEEL
test_poetry_nr-0.1.1.dist-info/RECORD
