Metadata-Version: 2.1
Name: test_poetry_nr
Version: 0.1.1
Summary: 
License: Proprietary.
Author: NR Person
Requires-Python: >=3.10,<3.12
Classifier: License :: Other/Proprietary License
Classifier: Programming Language :: Python :: 3
Classifier: Programming Language :: Python :: 3.10
Classifier: Programming Language :: Python :: 3.11
Requires-Dist: numpy (>=1.26.4,<2.0.0)
